dbio/__init__.py
dbio/cli.py
dbio/config.py
dbio/default_config.json
dbio/version.py
dbio/auth/__init__.py
dbio/auth/cli.py
dbio/dss/__init__.py
dbio/dss/cli.py
dbio/dss/error.py
dbio/dss/infra.py
dbio/dss/upload_to_cloud.py
dbio/dss/util/__init__.py
dbio/packages/__init__.py
dbio/util/__init__.py
dbio/util/_docs.py
dbio/util/compat.py
dbio/util/exceptions.py
dbio/util/fs_helper.py
dbio/util/pool.py
dbio/util/tsv.py
test/integration/__init__.py
test/integration/auth/__init__.py
test/integration/auth/test_auth_api.py
test/integration/dss/__init__.py
test/integration/dss/test_dss_api.py
test/integration/dss/test_dss_api_retry.py
test/integration/dss/test_dss_cli.py
test/integration/util/__init__.py
test/integration/util/test_swagger_client.py
test/unit/__init__.py
test/unit/test_dss_client.py
test/unit/util/__init__.py
test/unit/util/test_fs_helper.py
test/unit/util/test_swagger_client.py
dbio_cli-1.0.0.dist-info/LICENSE
dbio_cli-1.0.0.dist-info/METADATA
dbio_cli-1.0.0.dist-info/WHEEL
dbio_cli-1.0.0.dist-info/entry_points.txt
dbio_cli-1.0.0.dist-info/top_level.txt
dbio_cli-1.0.0.dist-info/RECORD
